<?xml version='1.0' encoding='UTF-8'?>
<odoo noupdate="1">
  <record id="x_allergies_1" model="x_allergies">
    <field name="x_name">Poultry-based treats</field>
  </record>
  <record id="x_allergies_2" model="x_allergies">
    <field name="x_name">Wheat / Grain</field>
  </record>
  <record id="x_allergies_3" model="x_allergies">
    <field name="x_name">Shampoo fragrance</field>
  </record>
  <record id="x_allergies_4" model="x_allergies">
    <field name="x_name">Contact to certain plastics</field>
  </record>
  <record id="x_allergies_5" model="x_allergies">
    <field name="x_name">Flea collars</field>
  </record>
  <record id="x_allergies_6" model="x_allergies">
    <field name="x_name">Dust mites</field>
  </record>
  <record id="x_allergies_7" model="x_allergies">
    <field name="x_name">Seasonal pollen</field>
  </record>
  <record id="x_allergies_8" model="x_allergies">
    <field name="x_name">Grooming products</field>
  </record>
  <record id="x_allergies_9" model="x_allergies">
    <field name="x_name">Ear cleaners</field>
  </record>
</odoo>
