<?xml version='1.0' encoding='UTF-8'?>
<odoo noupdate="1">
    <record id="documents_folder_17" model="documents.document">
        <field name="name">Internal</field>
        <field name="folder_id" search="[('id', '=', ref('documents_project.document_project_folder', raise_if_not_found=False))]"/>
        <field name="type">folder</field>
    </record>
    <record id="documents_folder_7" model="documents.document">
        <field name="name">3D scan</field>
        <field name="folder_id" search="[('id', '=', ref('documents_project.document_project_folder', raise_if_not_found=False))]"/>
        <field name="type">folder</field>
    </record>
    <record id="documents_folder_8" model="documents.document">
        <field name="name">Technical survey</field>
        <field name="folder_id" search="[('id', '=', ref('documents_project.document_project_folder', raise_if_not_found=False))]"/>
        <field name="type">folder</field>
    </record>
    <record id="documents_folder_9" model="documents.document">
        <field name="name">Planning permission</field>
        <field name="folder_id" search="[('id', '=', ref('documents_project.document_project_folder', raise_if_not_found=False))]"/>
        <field name="type">folder</field>
    </record>
</odoo>
