<?xml version='1.0' encoding='UTF-8'?>
<odoo noupdate="1">
  <record id="product_template_8" model="product.template">
    <field name="is_published" eval="True"/>
  </record>
  <record id="product_template_9" model="product.template">
    <field name="is_published" eval="True"/>
  </record>
  <record id="product_template_10" model="product.template">
    <field name="is_published" eval="True"/>
  </record>
  <record id="product_template_19" model="product.template">
    <field name="is_published" eval="True"/>
  </record>
  <record id="product_template_18" model="product.template">
    <field name="is_published" eval="True"/>
  </record>
  <record id="loyalty.gift_card_product_50_product_template" model="product.template" forcecreate="1">
    <field name="is_published" eval="True"/>
  </record>
  <record id="product_template_16" model="product.template">
    <field name="is_published" eval="True"/>
  </record>
  <record id="product_template_11" model="product.template">
    <field name="is_published" eval="True"/>
  </record>
  <record id="product_template_17" model="product.template">
    <field name="is_published" eval="True"/>
  </record>
  <record id="product_template_20" model="product.template">
    <field name="is_published" eval="True"/>
  </record>
  <record id="product_template_14" model="product.template">
    <field name="is_published" eval="True"/>
  </record>
  <record id="product_template_15" model="product.template">
    <field name="is_published" eval="True"/>
  </record>
  <record id="product_template_13" model="product.template">
    <field name="is_published" eval="True"/>
  </record>
</odoo>
