<?xml version='1.0' encoding='UTF-8'?>
<odoo>
    <function name="button_choose_theme" model="ir.module.module" eval="[ref('base.module_theme_orchid', raise_if_not_found=False) or ref('base.module_theme_default')]"/>
    <function model="ir.ui.view" name="write">
        <value model="ir.ui.view" eval="obj().env['website'].with_context(website_id=obj().env.ref('website.default_website').id).viewref('website.homepage').id"/>
        <value model="ir.ui.view" eval="{'arch': obj().env.ref('tattoo_shop.homepage').arch}"/>
    </function>
    <function model="ir.ui.view" name="write">
        <value model="ir.ui.view" eval="obj().env['website'].with_context(website_id=obj().env.ref('website.default_website').id).viewref('website.contactus').id" />
        <value model="ir.ui.view" eval="{'arch': obj().env.ref('tattoo_shop.contact_us').arch}" />
    </function>
    <function model="website.assets" name="make_scss_customization">
        <value eval="'/website/static/src/scss/options/colors/user_color_palette.scss'"/>
        <value eval="{'o-color-1': '#000000', 'o-color-2': '#c0392b', 'o-color-3': '#FFFFFF', 'o-color-4': '#FFFFFF', 'o-color-5': '#212529'}"/>
    </function>
</odoo>
