<?xml version='1.0' encoding='UTF-8'?>
<odoo noupdate="1" auto_sequence="1">
  <record id="sale_order_line_353" model="sale.order.line">
    <field name="order_id" ref="sale_order_128"/>
    <field name="display_type">line_section</field>
    <field name="name"><![CDATA[One-Time Fees]]></field>
    <field name="product_uom_qty" eval="False"/>
  </record>
  <record id="sale_order_line_354" model="sale.order.line">
    <field name="order_id" ref="sale_order_128"/>
    <field name="product_id" ref="product_product_4"/>
    <field name="name"><![CDATA[Kick-Off Fees
Contracts establishment
    Co-ownership creation in the software
    Act analysis
    Insurance analysis
    Identification forms creation
    Audit
    Opening/handover bank account(s) and company number
    Meters reading
    Call for funds and provisions
    Organization of general meeting]]></field>
  </record>
  <record id="sale_order_line_355" model="sale.order.line">
    <field name="order_id" ref="sale_order_128"/>
    <field name="display_type">line_section</field>
    <field name="name"><![CDATA[Recurring Fees]]></field>
    <field name="product_uom_qty" eval="False"/>
  </record>
  <record id="sale_order_line_356" model="sale.order.line">
    <field name="order_id" ref="sale_order_128"/>
    <field name="product_id" ref="product_product_15"/>
    <field name="name"><![CDATA[Recurring Service Fees
Approximately $50 per property per month, See Terms & Condition for further information about the coverage of the Service Fees]]></field>
  </record>
  <record id="sale_order_line_357" model="sale.order.line">
    <field name="order_id" ref="sale_order_128"/>
    <field name="display_type">line_section</field>
    <field name="name"><![CDATA[On-Demand Fees]]></field>
    <field name="product_uom_qty" eval="False"/>
  </record>
  <record id="sale_order_line_358" model="sale.order.line">
    <field name="order_id" ref="sale_order_128"/>
    <field name="product_id" ref="product_product_8"/>
    <field name="name"><![CDATA[Extraordinary General Meeting]]></field>
    <field name="product_uom_qty" eval="False"/>
  </record>
  <record id="sale_order_line_359" model="sale.order.line">
    <field name="order_id" ref="sale_order_128"/>
    <field name="product_id" ref="product_product_9"/>
    <field name="name"><![CDATA[Communication of information to the notary]]></field>
    <field name="product_uom_qty" eval="False"/>
  </record>
  <record id="sale_order_line_360" model="sale.order.line">
    <field name="order_id" ref="sale_order_128"/>
    <field name="product_id" ref="product_product_10"/>
    <field name="name"><![CDATA[First Reminder]]></field>
    <field name="product_uom_qty" eval="False"/>
  </record>
  <record id="sale_order_line_361" model="sale.order.line">
    <field name="order_id" ref="sale_order_128"/>
    <field name="product_id" ref="product_product_11"/>
    <field name="name"><![CDATA[Second Reminder
This does not include the fees from the ushers]]></field>
    <field name="product_uom_qty" eval="False"/>
  </record>
  <record id="sale_order_line_362" model="sale.order.line">
    <field name="order_id" ref="sale_order_128"/>
    <field name="product_id" ref="product_product_12"/>
    <field name="name"><![CDATA[Third Reminder
This does not include the fees from the ushers, lawyers, experts, etc.]]></field>
    <field name="product_uom_qty" eval="False"/>
  </record>
  <record id="sale_order_line_363" model="sale.order.line">
    <field name="order_id" ref="sale_order_128"/>
    <field name="product_id" ref="product_product_7"/>
    <field name="name"><![CDATA[Hourly Rate
All other extra services will be invoiced at the hourly rate, See Terms & Condition for further information about the hourly rate]]></field>
    <field name="product_uom_qty" eval="False"/>
    <field name="product_uom_id" ref="uom.product_uom_hour"/>
  </record>
  <record id="sale_order_line_324" model="sale.order.line">
    <field name="order_id" ref="sale_order_119"/>
    <field name="product_id" ref="product_product_808"/>
    <field name="name"><![CDATA[Archives fees]]></field>
  </record>
  <record id="sale_order_line_306" model="sale.order.line">
    <field name="order_id" ref="sale_order_112"/>
    <field name="product_id" ref="product_product_808"/>
    <field name="name"><![CDATA[Archives fees]]></field>
  </record>
  <record id="sale_order_line_288" model="sale.order.line">
    <field name="order_id" ref="sale_order_105"/>
    <field name="product_id" ref="product_product_712"/>
    <field name="name"><![CDATA[Auxiliary groups]]></field>
  </record>
  <record id="sale_order_line_269" model="sale.order.line">
    <field name="order_id" ref="sale_order_97"/>
    <field name="product_id" ref="product_product_784"/>
    <field name="name"><![CDATA[Architect/engineer fees]]></field>
  </record>
  <record id="sale_order_line_268" model="sale.order.line">
    <field name="order_id" ref="sale_order_95"/>
    <field name="product_id" ref="product_product_784"/>
    <field name="name"><![CDATA[Architect/engineer fees]]></field>
  </record>
  <record id="sale_order_line_335" model="sale.order.line">
    <field name="order_id" ref="sale_order_144"/>
    <field name="product_id" ref="product_product_15"/>
    <field name="name"><![CDATA[Monthly Service Fees
Approximately $80 per property per month, See Terms & Condition for further information about the coverage of the Service Fees]]></field>
    <field name="product_uom_qty">9.0</field>
  </record>
</odoo>
