<?xml version='1.0' encoding='UTF-8'?>
<odoo noupdate="1">
    <record id="sign_request_5" model="sign.request">
        <field name="template_id" ref="sign_template_6"/>
        <field name="subject">Signature Request - DISPLAY RIGHTS AGREEMENT(2).pdf</field>
        <field name="reference">DISPLAY RIGHTS AGREEMENT(2).pdf</field>
        <field name="state">signed</field>
        <field name="request_item_ids" eval="[
                Command.clear(),
                Command.create({
                'partner_id': ref('res_partner_15'),
                'role_id': ref('sign_item_role_6'),
                'state': 'completed',
                'signer_email': 'tomas.rivera@test.com',
                'signing_date': (DateTime.now() - timedelta(days=15)),
            }),
            Command.create({
                'partner_id': ref('base.main_partner'),
                'role_id': ref('sign_item_role_5'),
                'state': 'completed',
                'signer_email': '****@example.com',
                'signing_date': (DateTime.now() - timedelta(days=15)),
            })
        ]"/>
    </record>
</odoo>
